gnocchiclient/__init__.py
gnocchiclient/auth.py
gnocchiclient/benchmark.py
gnocchiclient/client.py
gnocchiclient/exceptions.py
gnocchiclient/gendoc.py
gnocchiclient/osc.py
gnocchiclient/shell.py
gnocchiclient/utils.py
gnocchiclient/version.py
gnocchiclient/tests/__init__.py
gnocchiclient/tests/functional/__init__.py
gnocchiclient/tests/functional/base.py
gnocchiclient/tests/functional/test_aggregates.py
gnocchiclient/tests/functional/test_archive_policy.py
gnocchiclient/tests/functional/test_archive_policy_rule.py
gnocchiclient/tests/functional/test_benchmark.py
gnocchiclient/tests/functional/test_capabilities.py
gnocchiclient/tests/functional/test_metric.py
gnocchiclient/tests/functional/test_osc.py
gnocchiclient/tests/functional/test_others.py
gnocchiclient/tests/functional/test_resource.py
gnocchiclient/tests/functional/test_resource_type.py
gnocchiclient/tests/unit/__init__.py
gnocchiclient/tests/unit/test_auth.py
gnocchiclient/tests/unit/test_exceptions.py
gnocchiclient/v1/__init__.py
gnocchiclient/v1/aggregates.py
gnocchiclient/v1/aggregates_cli.py
gnocchiclient/v1/archive_policy.py
gnocchiclient/v1/archive_policy_cli.py
gnocchiclient/v1/archive_policy_rule.py
gnocchiclient/v1/archive_policy_rule_cli.py
gnocchiclient/v1/base.py
gnocchiclient/v1/build.py
gnocchiclient/v1/build_cli.py
gnocchiclient/v1/capabilities.py
gnocchiclient/v1/capabilities_cli.py
gnocchiclient/v1/client.py
gnocchiclient/v1/metric.py
gnocchiclient/v1/metric_cli.py
gnocchiclient/v1/resource.py
gnocchiclient/v1/resource_cli.py
gnocchiclient/v1/resource_type.py
gnocchiclient/v1/resource_type_cli.py
gnocchiclient/v1/status.py
gnocchiclient/v1/status_cli.py
gnocchiclient-7.1.0.dist-info/LICENSE
gnocchiclient-7.1.0.dist-info/METADATA
gnocchiclient-7.1.0.dist-info/WHEEL
gnocchiclient-7.1.0.dist-info/entry_points.txt
gnocchiclient-7.1.0.dist-info/top_level.txt
gnocchiclient-7.1.0.dist-info/RECORD
