Metadata-Version: 2.1
Name: gnocchiclient
Version: 7.1.0
Summary: Python client library for Gnocchi
Home-page: http://gnocchi.osci.io/gnocchiclient
Author: Gnocchi
Classifier: Intended Audience :: Information Technology
Classifier: Intended Audience :: System Administrators
Classifier: License :: OSI Approved :: Apache Software License
Classifier: Operating System :: POSIX :: Linux
Classifier: Programming Language :: Python
Classifier: Programming Language :: Python :: 3
Classifier: Programming Language :: Python :: 3 :: Only
Classifier: Programming Language :: Python :: 3.8
Classifier: Programming Language :: Python :: 3.9
Classifier: Programming Language :: Python :: 3.10
Classifier: Programming Language :: Python :: 3.11
Classifier: Programming Language :: Python :: 3.12
License-File: LICENSE
Requires-Dist: cliff>=2.10
Requires-Dist: ujson
Requires-Dist: keystoneauth1>=2.0.0
Requires-Dist: futurist
Requires-Dist: iso8601
Requires-Dist: python-dateutil
Requires-Dist: debtcollector
Provides-Extra: doc
Requires-Dist: sphinx; extra == "doc"
Requires-Dist: sphinx-rtd-theme; extra == "doc"
Provides-Extra: openstack
Requires-Dist: osc-lib>=0.3.0; extra == "openstack"
Provides-Extra: test
Requires-Dist: python-openstackclient; extra == "test"
Requires-Dist: pytest; extra == "test"
Requires-Dist: pytest-xdist; extra == "test"
